pyDetektia/__init__.py
pyDetektia/manager.py
pydetektia-4.0.1.dist-info/licenses/LICENSE.txt
pydetektia-4.0.1.dist-info/METADATA
pydetektia-4.0.1.dist-info/WHEEL
pydetektia-4.0.1.dist-info/top_level.txt
pydetektia-4.0.1.dist-info/RECORD
