Metadata-Version: 2.4
Name: pyDetektia
Version: 4.0.1
Summary: A package for easily interaction with Detektia's API endpoints.
Home-page: https://github.com/detektia/pyDetektia
Author: Detektia
Author-email: info@detektia.com
License: ToBeChosen
License-File: LICENSE.txt
Requires-Dist: requests
Dynamic: author
Dynamic: author-email
Dynamic: description
Dynamic: description-content-type
Dynamic: home-page
Dynamic: license
Dynamic: license-file
Dynamic: requires-dist
Dynamic: summary
